{"skeleton":{"images":""},
"bones":[{"name":"root"}],
"slots":[
	{"name":"Weapon","bone":"root","attachment":"Weapon"},
	{"name":"Hand_L","bone":"root","attachment":"Hand_L"},
	{"name":"Arm_L","bone":"root","attachment":"Arm_L"},
	{"name":"Wing_2","bone":"root","attachment":"Wing_2"},
	{"name":"Wing_1","bone":"root","attachment":"Wing_1"},
	{"name":"Hood","bone":"root","attachment":"Hood"},
	{"name":"Shoescape_L","bone":"root","attachment":"Shoescape_L"},
	{"name":"Leg_L","bone":"root","attachment":"Leg_L"},
	{"name":"Body","bone":"root","attachment":"Body"},
	{"name":"Pocket_L","bone":"root","attachment":"Pocket_L"},
	{"name":"Pocket_R","bone":"root","attachment":"Pocket_R"},
	{"name":"Neckkara2","bone":"root","attachment":"Neckkara2"},
	{"name":"Neckkara1","bone":"root","attachment":"Neckkara1"},
	{"name":"Shoesback_R","bone":"root","attachment":"Shoesback_R"},
	{"name":"Leg_R","bone":"root","attachment":"Leg_R"},
	{"name":"Shoes_R","bone":"root","attachment":"Shoes_R"},
	{"name":"Shoescape_R","bone":"root","attachment":"Shoescape_R"},
	{"name":"Hand_R","bone":"root","attachment":"Hand_R"},
	{"name":"Arm_R","bone":"root","attachment":"Arm_R"},
	{"name":"ArmorArm_R","bone":"root","attachment":"ArmorArm_R"},
	{"name":"ArmorLeg_R","bone":"root","attachment":"ArmorLeg_R"},
	{"name":"Hair_Ponytail","bone":"root","attachment":"Hair_Ponytail"},
	{"name":"Hair_1","bone":"root","attachment":"Hair_1"},
	{"name":"Hair_Acc","bone":"root","attachment":"Hair_Acc"},
	{"name":"Hair_2","bone":"root","attachment":"Hair_2"},
	{"name":"Hair_3","bone":"root","attachment":"Hair_3"},
	{"name":"Hair_4","bone":"root","attachment":"Hair_4"},
	{"name":"Head","bone":"root","attachment":"Head"},
	{"name":"Eyebrow_L","bone":"root","attachment":"Eyebrow_L"},
	{"name":"Eyebrow_R","bone":"root","attachment":"Eyebrow_R"},
	{"name":"Mouth","bone":"root","attachment":"Mouth"},
	{"name":"Eye_L","bone":"root","attachment":"Eye_L"},
	{"name":"Eye_pupil_L","bone":"root","attachment":"Eye_pupil_L"},
	{"name":"Eye_skin_L","bone":"root","attachment":"Eye_skin_L"},
	{"name":"Eye_lashes_L","bone":"root","attachment":"Eye_lashes_L"},
	{"name":"Eyeclose_L","bone":"root","attachment":"Eyeclose_L"},
	{"name":"Eye_R","bone":"root","attachment":"Eye_R"},
	{"name":"Eye_pupil_R","bone":"root","attachment":"Eye_pupil_R"},
	{"name":"Eye_skin_R","bone":"root","attachment":"Eye_skin_R"},
	{"name":"Eye_lashes_R","bone":"root","attachment":"Eye_lashes_R"},
	{"name":"Eyeclose_R","bone":"root","attachment":"Eyeclose_R"},
	{"name":"Hair_5","bone":"root","attachment":"Hair_5"},
	{"name":"Hair_6","bone":"root","attachment":"Hair_6"},
	{"name":"Hair_7","bone":"root","attachment":"Hair_7"},
	{"name":"Hair_8","bone":"root","attachment":"Hair_8"},
	{"name":"Effect","bone":"root","attachment":"Effect"}
],
"skins":{
	"default":{
		"Effect":{"Effect":{"x":549.5,"y":732,"width":957,"height":1316}},
		"Hair_8":{"Hair_8":{"x":1152.5,"y":919.5,"width":121,"height":95}},
		"Hair_7":{"Hair_7":{"x":1256.5,"y":872.5,"width":151,"height":191}},
		"Hair_6":{"Hair_6":{"x":1216.5,"y":904.5,"width":111,"height":125}},
		"Hair_5":{"Hair_5":{"x":1150.5,"y":932.5,"width":83,"height":73}},
		"Eyeclose_R":{"Eyeclose_R":{"x":1214.5,"y":848,"width":53,"height":48}},
		"Eye_lashes_R":{"Eye_lashes_R":{"x":1216,"y":846.5,"width":42,"height":45}},
		"Eye_skin_R":{"Eye_skin_R":{"x":1216,"y":847.5,"width":50,"height":47}},
		"Eye_pupil_R":{"Eye_pupil_R":{"x":1216.5,"y":842.5,"width":31,"height":31}},
		"Eye_R":{"Eye_R":{"x":1214,"y":848,"width":46,"height":46}},
		"Eyeclose_L":{"Eyeclose_L":{"x":1151,"y":851.5,"width":34,"height":49}},
		"Eye_lashes_L":{"Eye_lashes_L":{"x":1148,"y":852,"width":36,"height":48}},
		"Eye_skin_L":{"Eye_skin_L":{"x":1152,"y":852,"width":38,"height":54}},
		"Eye_pupil_L":{"Eye_pupil_L":{"x":1155.5,"y":845.5,"width":23,"height":31}},
		"Eye_L":{"Eye_L":{"x":1153,"y":847,"width":30,"height":36}},
		"Mouth":{"Mouth":{"x":1186,"y":804.5,"width":54,"height":33}},
		"Eyebrow_R":{"Eyebrow_R":{"x":1199,"y":878.5,"width":30,"height":21}},
		"Eyebrow_L":{"Eyebrow_L":{"x":1149.5,"y":880.5,"width":21,"height":19}},
		"Head":{"Head":{"x":1213,"y":859.5,"width":174,"height":155}},
		"Hair_4":{"Hair_4":{"x":1116.5,"y":870.5,"width":121,"height":143}},
		"Hair_3":{"Hair_3":{"x":1100,"y":906.5,"width":138,"height":87}},
		"Hair_2":{"Hair_2":{"x":1103,"y":1009.5,"width":182,"height":105}},
		"Hair_Acc":{"Hair_Acc":{"x":1215,"y":963,"width":182,"height":98}},
		"Hair_1":{"Hair_1":{"x":1260.5,"y":894.5,"width":225,"height":165}},
		"Hair_Ponytail":{"Hair_Ponytail":{"x":1301,"y":1039.5,"width":230,"height":159}},
		"ArmorLeg_R":{"ArmorLeg_R":{"x":1237,"y":397,"width":132,"height":114}},
		"ArmorArm_R":{"ArmorArm_R":{"x":1418,"y":782,"width":78,"height":48}},
		"Arm_R":{"Arm_R":{"x":1458.5,"y":754,"width":347,"height":148}},
		"Hand_R":{"Hand_R":{"x":1646,"y":725,"width":82,"height":92}},
		"Shoescape_R":{"Shoescape_R":{"x":1171.5,"y":171,"width":125,"height":70}},
		"Shoes_R":{"Shoes_R":{"x":1097.5,"y":139,"width":113,"height":102}},
		"Leg_R":{"Leg_R":{"x":1301,"y":381.5,"width":422,"height":501}},
		"Shoesback_R":{"Shoesback_R":{"x":1160.5,"y":200.5,"width":147,"height":109}},
		"Neckkara1":{"Neckkara1":{"x":1219,"y":798.5,"width":102,"height":65}},
		"Neckkara2":{"Neckkara2":{"x":1175,"y":734.5,"width":270,"height":179}},
		"Pocket_R":{"Pocket_R":{"x":1431,"y":647,"width":128,"height":40}},
		"Pocket_L":{"Pocket_L":{"x":1250,"y":651,"width":58,"height":46}},
		"Body":{"Body":{"x":1337.5,"y":693.5,"width":295,"height":249}},
		"Leg_L":{"Leg_L":{"x":1111,"y":513,"width":512,"height":270}},
		"Shoescape_L":{"Shoescape_L":{"x":975,"y":475,"width":94,"height":148}},
		"Hood":{"Hood":{"x":1312.5,"y":809.5,"width":181,"height":133}},
		"Wing_1":{"Wing_1":{"x":1522.5,"y":971,"width":497,"height":364}},
		"Wing_2":{"Wing_2":{"x":1582,"y":757.5,"width":542,"height":245}},
		"Arm_L":{"Arm_L":{"x":1215.5,"y":915.5,"width":123,"height":359}},
		"Hand_L":{"Hand_L":{"x":1263,"y":1118,"width":70,"height":88}},
		"Weapon":{"Weapon":{"x":840,"y":1183,"width":1272,"height":354}}
	}
},
"animations":{"animation":{}}
}